{
  "service": {
    "service": "webiny-website-services",
    "serviceObject": {
      "name": "webiny-website-services"
    },
    "provider": {
      "stage": "dev",
      "region": "us-east-1",
      "variableSyntax": "\\${([ ~:a-zA-Z0-9._'\",\\-\\/\\(\\)]+?)}",
      "name": "aws",
      "runtime": "nodejs6.10",
      "iamRoleStatements": [
        {
          "Effect": "Allow",
          "Action": [
            "ses:SendEmail"
          ],
          "Resource": [
            "arn:aws:ses:us-east-1:*"
          ]
        }
      ],
      "versionFunctions": true,
      "remoteFunctionData": null,
      "compiledCloudFormationTemplate": {
        "AWSTemplateFormatVersion": "2010-09-09",
        "Description": "The AWS CloudFormation template for this Serverless application",
        "Resources": {
          "ServerlessDeploymentBucket": {
            "Type": "AWS::S3::Bucket"
          },
          "SubscribeLogGroup": {
            "Type": "AWS::Logs::LogGroup",
            "Properties": {
              "LogGroupName": "/aws/lambda/webiny-website-services-dev-subscribe"
            }
          },
          "ContactDashusLogGroup": {
            "Type": "AWS::Logs::LogGroup",
            "Properties": {
              "LogGroupName": "/aws/lambda/webiny-website-services-dev-contact-us"
            }
          },
          "IamRoleLambdaExecution": {
            "Type": "AWS::IAM::Role",
            "Properties": {
              "AssumeRolePolicyDocument": {
                "Version": "2012-10-17",
                "Statement": [
                  {
                    "Effect": "Allow",
                    "Principal": {
                      "Service": [
                        "lambda.amazonaws.com"
                      ]
                    },
                    "Action": [
                      "sts:AssumeRole"
                    ]
                  }
                ]
              },
              "Policies": [
                {
                  "PolicyName": {
                    "Fn::Join": [
                      "-",
                      [
                        "dev",
                        "webiny-website-services",
                        "lambda"
                      ]
                    ]
                  },
                  "PolicyDocument": {
                    "Version": "2012-10-17",
                    "Statement": [
                      {
                        "Effect": "Allow",
                        "Action": [
                          "logs:CreateLogStream"
                        ],
                        "Resource": [
                          {
                            "Fn::Sub": "arn:${AWS::Partition}:logs:${AWS::Region}:${AWS::AccountId}:log-group:/aws/lambda/webiny-website-services-dev-subscribe:*"
                          },
                          {
                            "Fn::Sub": "arn:${AWS::Partition}:logs:${AWS::Region}:${AWS::AccountId}:log-group:/aws/lambda/webiny-website-services-dev-contact-us:*"
                          }
                        ]
                      },
                      {
                        "Effect": "Allow",
                        "Action": [
                          "logs:PutLogEvents"
                        ],
                        "Resource": [
                          {
                            "Fn::Sub": "arn:${AWS::Partition}:logs:${AWS::Region}:${AWS::AccountId}:log-group:/aws/lambda/webiny-website-services-dev-subscribe:*:*"
                          },
                          {
                            "Fn::Sub": "arn:${AWS::Partition}:logs:${AWS::Region}:${AWS::AccountId}:log-group:/aws/lambda/webiny-website-services-dev-contact-us:*:*"
                          }
                        ]
                      },
                      {
                        "$ref": "$[\"service\"][\"provider\"][\"iamRoleStatements\"][0]"
                      }
                    ]
                  }
                }
              ],
              "Path": "/",
              "RoleName": {
                "Fn::Join": [
                  "-",
                  [
                    "webiny-website-services",
                    "dev",
                    "us-east-1",
                    "lambdaRole"
                  ]
                ]
              }
            }
          },
          "SubscribeLambdaFunction": {
            "Type": "AWS::Lambda::Function",
            "Properties": {
              "Code": {
                "S3Bucket": {
                  "Ref": "ServerlessDeploymentBucket"
                },
                "S3Key": "serverless/webiny-website-services/dev/1532205814617-2018-07-21T20:43:34.617Z/webiny-website-services.zip"
              },
              "FunctionName": "webiny-website-services-dev-subscribe",
              "Handler": "subscribe.handler",
              "MemorySize": 1024,
              "Role": {
                "Fn::GetAtt": [
                  "IamRoleLambdaExecution",
                  "Arn"
                ]
              },
              "Runtime": "nodejs6.10",
              "Timeout": 6
            },
            "DependsOn": [
              "SubscribeLogGroup",
              "IamRoleLambdaExecution"
            ]
          },
          "SubscribeLambdaVersioncFL8UUue8ltzva8vFWsKlxmDZdfDRtCfbk3LhxHx6M": {
            "Type": "AWS::Lambda::Version",
            "DeletionPolicy": "Retain",
            "Properties": {
              "FunctionName": {
                "Ref": "SubscribeLambdaFunction"
              },
              "CodeSha256": "EUJMygo6KfAToFR/vQUQmB5rfm1R52gKJXn0BCLvaBk="
            }
          },
          "ContactDashusLambdaFunction": {
            "Type": "AWS::Lambda::Function",
            "Properties": {
              "Code": {
                "S3Bucket": {
                  "Ref": "ServerlessDeploymentBucket"
                },
                "S3Key": "serverless/webiny-website-services/dev/1532205814617-2018-07-21T20:43:34.617Z/webiny-website-services.zip"
              },
              "FunctionName": "webiny-website-services-dev-contact-us",
              "Handler": "contact-us.handler",
              "MemorySize": 1024,
              "Role": {
                "Fn::GetAtt": [
                  "IamRoleLambdaExecution",
                  "Arn"
                ]
              },
              "Runtime": "nodejs6.10",
              "Timeout": 6
            },
            "DependsOn": [
              "ContactDashusLogGroup",
              "IamRoleLambdaExecution"
            ]
          },
          "ContactDashusLambdaVersion61ymRmEO9Uo5rdzCSra4Boem0yTIGnwrDWm5AmsLH4": {
            "Type": "AWS::Lambda::Version",
            "DeletionPolicy": "Retain",
            "Properties": {
              "FunctionName": {
                "Ref": "ContactDashusLambdaFunction"
              },
              "CodeSha256": "EUJMygo6KfAToFR/vQUQmB5rfm1R52gKJXn0BCLvaBk="
            }
          },
          "ApiGatewayRestApi": {
            "Type": "AWS::ApiGateway::RestApi",
            "Properties": {
              "Name": "dev-webiny-website-services",
              "EndpointConfiguration": {
                "Types": [
                  "EDGE"
                ]
              }
            }
          },
          "ApiGatewayResourceSubscribe": {
            "Type": "AWS::ApiGateway::Resource",
            "Properties": {
              "ParentId": {
                "Fn::GetAtt": [
                  "ApiGatewayRestApi",
                  "RootResourceId"
                ]
              },
              "PathPart": "subscribe",
              "RestApiId": {
                "Ref": "ApiGatewayRestApi"
              }
            }
          },
          "ApiGatewayResourceContactDashus": {
            "Type": "AWS::ApiGateway::Resource",
            "Properties": {
              "ParentId": {
                "Fn::GetAtt": [
                  "ApiGatewayRestApi",
                  "RootResourceId"
                ]
              },
              "PathPart": "contact-us",
              "RestApiId": {
                "Ref": "ApiGatewayRestApi"
              }
            }
          },
          "ApiGatewayMethodSubscribePost": {
            "Type": "AWS::ApiGateway::Method",
            "Properties": {
              "HttpMethod": "POST",
              "RequestParameters": {},
              "ResourceId": {
                "Ref": "ApiGatewayResourceSubscribe"
              },
              "RestApiId": {
                "Ref": "ApiGatewayRestApi"
              },
              "ApiKeyRequired": false,
              "AuthorizationType": "NONE",
              "Integration": {
                "IntegrationHttpMethod": "POST",
                "Type": "AWS_PROXY",
                "Uri": {
                  "Fn::Join": [
                    "",
                    [
                      "arn:",
                      {
                        "Ref": "AWS::Partition"
                      },
                      ":apigateway:",
                      {
                        "Ref": "AWS::Region"
                      },
                      ":lambda:path/2015-03-31/functions/",
                      {
                        "Fn::GetAtt": [
                          "SubscribeLambdaFunction",
                          "Arn"
                        ]
                      },
                      "/invocations"
                    ]
                  ]
                }
              },
              "MethodResponses": []
            }
          },
          "ApiGatewayMethodContactDashusPost": {
            "Type": "AWS::ApiGateway::Method",
            "Properties": {
              "HttpMethod": "POST",
              "RequestParameters": {},
              "ResourceId": {
                "Ref": "ApiGatewayResourceContactDashus"
              },
              "RestApiId": {
                "Ref": "ApiGatewayRestApi"
              },
              "ApiKeyRequired": false,
              "AuthorizationType": "NONE",
              "Integration": {
                "IntegrationHttpMethod": "POST",
                "Type": "AWS_PROXY",
                "Uri": {
                  "Fn::Join": [
                    "",
                    [
                      "arn:",
                      {
                        "Ref": "AWS::Partition"
                      },
                      ":apigateway:",
                      {
                        "Ref": "AWS::Region"
                      },
                      ":lambda:path/2015-03-31/functions/",
                      {
                        "Fn::GetAtt": [
                          "ContactDashusLambdaFunction",
                          "Arn"
                        ]
                      },
                      "/invocations"
                    ]
                  ]
                }
              },
              "MethodResponses": []
            }
          },
          "ApiGatewayDeployment1532205814752": {
            "Type": "AWS::ApiGateway::Deployment",
            "Properties": {
              "RestApiId": {
                "Ref": "ApiGatewayRestApi"
              },
              "StageName": "dev"
            },
            "DependsOn": [
              "ApiGatewayMethodSubscribePost",
              "ApiGatewayMethodContactDashusPost"
            ]
          },
          "SubscribeLambdaPermissionApiGateway": {
            "Type": "AWS::Lambda::Permission",
            "Properties": {
              "FunctionName": {
                "Fn::GetAtt": [
                  "SubscribeLambdaFunction",
                  "Arn"
                ]
              },
              "Action": "lambda:InvokeFunction",
              "Principal": {
                "Fn::Join": [
                  "",
                  [
                    "apigateway.",
                    {
                      "Ref": "AWS::URLSuffix"
                    }
                  ]
                ]
              },
              "SourceArn": {
                "Fn::Join": [
                  "",
                  [
                    "arn:",
                    {
                      "Ref": "AWS::Partition"
                    },
                    ":execute-api:",
                    {
                      "Ref": "AWS::Region"
                    },
                    ":",
                    {
                      "Ref": "AWS::AccountId"
                    },
                    ":",
                    {
                      "Ref": "ApiGatewayRestApi"
                    },
                    "/*/*"
                  ]
                ]
              }
            }
          },
          "ContactDashusLambdaPermissionApiGateway": {
            "Type": "AWS::Lambda::Permission",
            "Properties": {
              "FunctionName": {
                "Fn::GetAtt": [
                  "ContactDashusLambdaFunction",
                  "Arn"
                ]
              },
              "Action": "lambda:InvokeFunction",
              "Principal": {
                "Fn::Join": [
                  "",
                  [
                    "apigateway.",
                    {
                      "Ref": "AWS::URLSuffix"
                    }
                  ]
                ]
              },
              "SourceArn": {
                "Fn::Join": [
                  "",
                  [
                    "arn:",
                    {
                      "Ref": "AWS::Partition"
                    },
                    ":execute-api:",
                    {
                      "Ref": "AWS::Region"
                    },
                    ":",
                    {
                      "Ref": "AWS::AccountId"
                    },
                    ":",
                    {
                      "Ref": "ApiGatewayRestApi"
                    },
                    "/*/*"
                  ]
                ]
              }
            }
          }
        },
        "Outputs": {
          "ServerlessDeploymentBucketName": {
            "Value": {
              "Ref": "ServerlessDeploymentBucket"
            }
          },
          "SubscribeLambdaFunctionQualifiedArn": {
            "Description": "Current Lambda function version",
            "Value": {
              "Ref": "SubscribeLambdaVersioncFL8UUue8ltzva8vFWsKlxmDZdfDRtCfbk3LhxHx6M"
            }
          },
          "ContactDashusLambdaFunctionQualifiedArn": {
            "Description": "Current Lambda function version",
            "Value": {
              "Ref": "ContactDashusLambdaVersion61ymRmEO9Uo5rdzCSra4Boem0yTIGnwrDWm5AmsLH4"
            }
          },
          "ServiceEndpoint": {
            "Description": "URL of the service endpoint",
            "Value": {
              "Fn::Join": [
                "",
                [
                  "https://",
                  {
                    "Ref": "ApiGatewayRestApi"
                  },
                  ".execute-api.us-east-1.",
                  {
                    "Ref": "AWS::URLSuffix"
                  },
                  "/dev"
                ]
              ]
            }
          }
        }
      },
      "coreCloudFormationTemplate": {
        "AWSTemplateFormatVersion": "2010-09-09",
        "Description": "The AWS CloudFormation template for this Serverless application",
        "Resources": {
          "ServerlessDeploymentBucket": {
            "Type": "AWS::S3::Bucket"
          }
        },
        "Outputs": {
          "ServerlessDeploymentBucketName": {
            "Value": {
              "Ref": "ServerlessDeploymentBucket"
            }
          }
        }
      },
      "vpc": {}
    },
    "custom": {
      "serverless-offline": {
        "port": 4000
      }
    },
    "plugins": [
      "serverless-offline"
    ],
    "pluginsData": {},
    "functions": {
      "subscribe": {
        "handler": "subscribe.handler",
        "events": [
          {
            "http": {
              "path": "subscribe",
              "method": "post",
              "integration": "AWS_PROXY"
            }
          }
        ],
        "name": "webiny-website-services-dev-subscribe",
        "package": {},
        "memory": 1024,
        "timeout": 6,
        "runtime": "nodejs6.10",
        "vpc": {}
      },
      "contact-us": {
        "handler": "contact-us.handler",
        "events": [
          {
            "http": {
              "path": "contact-us",
              "method": "post",
              "integration": "AWS_PROXY"
            }
          }
        ],
        "name": "webiny-website-services-dev-contact-us",
        "package": {},
        "memory": 1024,
        "timeout": 6,
        "runtime": "nodejs6.10",
        "vpc": {}
      }
    },
    "artifact": "/Users/sven/webiny/gatsby/webiny/services/.serverless/webiny-website-services.zip"
  },
  "package": {
    "artifactDirectoryName": "serverless/webiny-website-services/dev/1532205814617-2018-07-21T20:43:34.617Z",
    "artifact": "webiny-website-services.zip"
  }
}